LICENSE
MANIFEST.in
README.md
setup.py
forecaster/__init__.py
forecaster/fitting_parameters.h5
forecaster/forecaster.py
forecaster_plus.egg-info/PKG-INFO
forecaster_plus.egg-info/SOURCES.txt
forecaster_plus.egg-info/dependency_links.txt
forecaster_plus.egg-info/requires.txt
forecaster_plus.egg-info/top_level.txt