Metadata-Version: 2.1
Name: forecaster-plus
Version: 1.1.0
Summary: Probabilistically forecast astronomical masses and radii
Home-page: https://github.com/ben-cassese/forecaster-plus
Author: Ben Cassese
Author-email: b.c.cassese@columbia.edu
License: MIT
Platform: UNKNOWN
License-File: LICENSE
